{"179": {"0": {"idx": 0, "max": 0.10171, "counts": 322}, "1800": {"idx": 1, "max": 0.10176, "counts": 640}, "3600": {"idx": 2, "max": 0.19139, "counts": 1136}, "5400": {"idx": 3, "max": 0.49573, "counts": 1862}, "7200": {"idx": 4, "max": 0.24033, "counts": 2219}, "9000": {"idx": 5, "max": 0.30135, "counts": 2564}, "10800": {"idx": 6, "max": 0.27593, "counts": 2902}, "12600": {"idx": 7, "max": 0.46751, "counts": 3132}, "14400": {"idx": 8, "max": 0.53535, "counts": 2501}, "16200": {"idx": 9, "max": 0.34717, "counts": 1992}, "18000": {"idx": 10, "max": 0.20256, "counts": 1873}, "19800": {"idx": 11, "max": 0.25318, "counts": 2298}, "21600": {"idx": 12, "max": 0.28262, "counts": 3133}, "23400": {"idx": 13, "max": 0.34263, "counts": 3204}, "25200": {"idx": 14, "max": 0.34063, "counts": 2218}, "27000": {"idx": 15, "max": 0.12173, "counts": 1831}, "28800": {"idx": 16, "max": 0.19542, "counts": 1905}, "30600": {"idx": 17, "max": 0.15509, "counts": 1950}, "32400": {"idx": 18, "max": 0.22142, "counts": 2032}, "34200": {"idx": 19, "max": 0.47687, "counts": 2046}, "36000": {"idx": 20, "max": 0.3006, "counts": 1345}, "37800": {"idx": 21, "max": 0.1873, "counts": 1287}, "39600": {"idx": 22, "max": 0.14882, "counts": 1372}, "41400": {"idx": 23, "max": 0.23024, "counts": 1341}, "43200": {"idx": 24, "max": 0.18113, "counts": 1534}, "45000": {"idx": 25, "max": 0.22338, "counts": 2177}, "46800": {"idx": 26, "max": 0.31149, "counts": 2422}, "48600": {"idx": 27, "max": 0.88466, "counts": 2804}, "50400": {"idx": 28, "max": 1.4403, "counts": 3043}, "52200": {"idx": 29, "max": 0.96772, "counts": 2558}, "54000": {"idx": 30, "max": 0.78508, "counts": 2204}, "55800": {"idx": 31, "max": 0.95299, "counts": 2000}, "57600": {"idx": 32, "max": 0.48029, "counts": 1711}, "59400": {"idx": 33, "max": 0.52193, "counts": 1577}, "61200": {"idx": 34, "max": 0.51526, "counts": 1524}, "63000": {"idx": 35, "max": 0.4286, "counts": 1513}, "64800": {"idx": 36, "max": 0.33301, "counts": 1363}, "66600": {"idx": 37, "max": 0.30882, "counts": 1429}, "68400": {"idx": 38, "max": 0.36678, "counts": 1482}, "70200": {"idx": 39, "max": 0.31546, "counts": 1564}, "72000": {"idx": 40, "max": 0.28663, "counts": 1652}, "73800": {"idx": 41, "max": 0.34138, "counts": 1725}, "75600": {"idx": 42, "max": 0.25295, "counts": 1817}, "77400": {"idx": 43, "max": 0.54421, "counts": 2038}, "79200": {"idx": 44, "max": 0.54157, "counts": 2198}, "81000": {"idx": 45, "max": 0.63816, "counts": 2395}, "82800": {"idx": 46, "max": 0.53782, "counts": 2497}, "84600": {"idx": 47, "max": 0.82095, "counts": 2649}, "86400": {"idx": 48, "max": 0.84436, "counts": 2912}, "88200": {"idx": 49, "max": 0.83336, "counts": 3008}, "90000": {"idx": 50, "max": 1.0269, "counts": 3185}, "91800": {"idx": 51, "max": 0.8637, "counts": 3181}, "93600": {"idx": 52, "max": 0.91814, "counts": 3254}, "95400": {"idx": 53, "max": 1.02947, "counts": 3399}, "97200": {"idx": 54, "max": 0.52174, "counts": 3395}, "99000": {"idx": 55, "max": 0.62228, "counts": 3555}, "100800": {"idx": 56, "max": 0.65619, "counts": 3662}, "102600": {"idx": 57, "max": 0.90748, "counts": 5616}, "104400": {"idx": 58, "max": 1.19511, "counts": 6354}, "106200": {"idx": 59, "max": 1.41255, "counts": 6112}, "108000": {"idx": 60, "max": 1.22573, "counts": 5910}, "109800": {"idx": 61, "max": 1.07317, "counts": 5635}, "111600": {"idx": 62, "max": 1.09713, "counts": 5286}, "113400": {"idx": 63, "max": 1.13021, "counts": 5260}, "115200": {"idx": 64, "max": 1.10356, "counts": 5092}, "117000": {"idx": 65, "max": 0.85973, "counts": 4987}, "118800": {"idx": 66, "max": 0.97508, "counts": 4989}, "120600": {"idx": 67, "max": 1.12183, "counts": 5111}, "122400": {"idx": 68, "max": 1.37349, "counts": 4925}, "124200": {"idx": 69, "max": 1.60294, "counts": 4938}, "126000": {"idx": 70, "max": 1.87438, "counts": 5040}, "127800": {"idx": 71, "max": 2.06372, "counts": 5124}, "129600": {"idx": 72, "max": 2.19061, "counts": 4999}, "131400": {"idx": 73, "max": 1.8412, "counts": 4709}, "133200": {"idx": 74, "max": 1.83253, "counts": 4547}, "135000": {"idx": 75, "max": 1.72, "counts": 4294}, "136800": {"idx": 76, "max": 1.15827, "counts": 4069}, "138600": {"idx": 77, "max": 1.02231, "counts": 3783}, "140400": {"idx": 78, "max": 0.95277, "counts": 3371}, "142200": {"idx": 79, "max": 0.92055, "counts": 3221}, "144000": {"idx": 80, "max": 0.87902, "counts": 3095}, "145800": {"idx": 81, "max": 0.68132, "counts": 2872}, "147600": {"idx": 82, "max": 0.77901, "counts": 2858}, "149400": {"idx": 83, "max": 0.5384, "counts": 2704}, "151200": {"idx": 84, "max": 0.53401, "counts": 2712}, "153000": {"idx": 85, "max": 0.49376, "counts": 2709}, "154800": {"idx": 86, "max": 0.47958, "counts": 2752}, "156600": {"idx": 87, "max": 0.50614, "counts": 2838}, "158400": {"idx": 88, "max": 0.48249, "counts": 2813}, "160200": {"idx": 89, "max": 0.53213, "counts": 3060}, "162000": {"idx": 90, "max": 0.46303, "counts": 3309}, "163800": {"idx": 91, "max": 0.59061, "counts": 3536}, "165600": {"idx": 92, "max": 0.56565, "counts": 3679}, "167400": {"idx": 93, "max": 0.65495, "counts": 3815}, "169200": {"idx": 94, "max": 0.76958, "counts": 4097}, "171000": {"idx": 95, "max": 0.89931, "counts": 4176}, "172800": {"idx": 96, "max": 0.74127, "counts": 4284}, "174600": {"idx": 97, "max": 0.7231, "counts": 4495}, "176400": {"idx": 98, "max": 0.76087, "counts": 4582}, "178200": {"idx": 99, "max": 0.65208, "counts": 4898}, "180000": {"idx": 100, "max": 0.75396, "counts": 4912}, "181800": {"idx": 101, "max": 0.7017, "counts": 4803}, "183600": {"idx": 102, "max": 0.7801, "counts": 4782}, "185400": {"idx": 103, "max": 0.74119, "counts": 4418}, "187200": {"idx": 104, "max": 0.7309, "counts": 4594}, "189000": {"idx": 105, "max": 0.89265, "counts": 4703}, "190800": {"idx": 106, "max": 0.91414, "counts": 4612}, "192600": {"idx": 107, "max": 0.85818, "counts": 4632}, "194400": {"idx": 108, "max": 0.96583, "counts": 4567}, "196200": {"idx": 109, "max": 1.12475, "counts": 4340}, "198000": {"idx": 110, "max": 0.83154, "counts": 4265}, "199800": {"idx": 111, "max": 0.8017, "counts": 4481}, "201600": {"idx": 112, "max": 0.81191, "counts": 4373}, "203400": {"idx": 113, "max": 0.98358, "counts": 4451}, "205200": {"idx": 114, "max": 0.90359, "counts": 4265}, "207000": {"idx": 115, "max": 0.9575, "counts": 4157}, "208800": {"idx": 116, "max": 0.99665, "counts": 4073}, "210600": {"idx": 117, "max": 1.15283, "counts": 4005}, "212400": {"idx": 118, "max": 1.06526, "counts": 3940}, "214200": {"idx": 119, "max": 1.05998, "counts": 3758}, "216000": {"idx": 120, "max": 0.82649, "counts": 3592}, "217800": {"idx": 121, "max": 0.85327, "counts": 3416}, "219600": {"idx": 122, "max": 0.66808, "counts": 2956}, "221400": {"idx": 123, "max": 0.56698, "counts": 2818}, "223200": {"idx": 124, "max": 0.45136, "counts": 2648}, "225000": {"idx": 125, "max": 0.47667, "counts": 2413}, "226800": {"idx": 126, "max": 0.29247, "counts": 2268}, "228600": {"idx": 127, "max": 0.51618, "counts": 2053}, "230400": {"idx": 128, "max": 0.3446, "counts": 2005}, "232200": {"idx": 129, "max": 0.45062, "counts": 2011}, "234000": {"idx": 130, "max": 0.33949, "counts": 2137}, "235800": {"idx": 131, "max": 0.4707, "counts": 2270}, "237600": {"idx": 132, "max": 0.62851, "counts": 2336}, "239400": {"idx": 133, "max": 0.63409, "counts": 2490}, "241200": {"idx": 134, "max": 0.5591, "counts": 2500}, "243000": {"idx": 135, "max": 0.77336, "counts": 2635}, "244800": {"idx": 136, "max": 0.73282, "counts": 2825}, "246600": {"idx": 137, "max": 0.9561, "counts": 3029}, "248400": {"idx": 138, "max": 0.79992, "counts": 2946}, "250200": {"idx": 139, "max": 0.84025, "counts": 3050}, "252000": {"idx": 140, "max": 0.86416, "counts": 3009}, "253800": {"idx": 141, "max": 0.95702, "counts": 3024}, "255600": {"idx": 142, "max": 0.79903, "counts": 2879}, "257400": {"idx": 143, "max": 0.6482, "counts": 2753}, "259200": {"idx": 144, "max": 0.00817, "counts": 1}}}