{"301": {"0": {"idx": 0, "max": 0.10023, "counts": 276}, "1800": {"idx": 1, "max": 0.08237, "counts": 581}, "3600": {"idx": 2, "max": 0.14538, "counts": 920}, "5400": {"idx": 3, "max": 0.54479, "counts": 1507}, "7200": {"idx": 4, "max": 0.98899, "counts": 2268}, "9000": {"idx": 5, "max": 0.81847, "counts": 2639}, "10800": {"idx": 6, "max": 0.94229, "counts": 2802}, "12600": {"idx": 7, "max": 0.82805, "counts": 2848}, "14400": {"idx": 8, "max": 0.97173, "counts": 2056}, "16200": {"idx": 9, "max": 0.66124, "counts": 1625}, "18000": {"idx": 10, "max": 0.64471, "counts": 1520}, "19800": {"idx": 11, "max": 0.97681, "counts": 1932}, "21600": {"idx": 12, "max": 1.49467, "counts": 2584}, "23400": {"idx": 13, "max": 1.56351, "counts": 2650}, "25200": {"idx": 14, "max": 0.97128, "counts": 1846}, "27000": {"idx": 15, "max": 0.74136, "counts": 1509}, "28800": {"idx": 16, "max": 0.63191, "counts": 1443}, "30600": {"idx": 17, "max": 0.7539, "counts": 1459}, "32400": {"idx": 18, "max": 0.75964, "counts": 1508}, "34200": {"idx": 19, "max": 0.59288, "counts": 1444}, "36000": {"idx": 20, "max": 0.43532, "counts": 899}, "37800": {"idx": 21, "max": 0.45249, "counts": 819}, "39600": {"idx": 22, "max": 0.37498, "counts": 819}, "41400": {"idx": 23, "max": 0.31158, "counts": 763}, "43200": {"idx": 24, "max": 0.36159, "counts": 806}, "45000": {"idx": 25, "max": 0.34626, "counts": 1048}, "46800": {"idx": 26, "max": 0.19097, "counts": 944}, "48600": {"idx": 27, "max": 0.26627, "counts": 916}, "50400": {"idx": 28, "max": 0.14518, "counts": 853}, "52200": {"idx": 29, "max": 0.18628, "counts": 819}, "54000": {"idx": 30, "max": 0.13442, "counts": 768}, "55800": {"idx": 31, "max": 0.16172, "counts": 760}, "57600": {"idx": 32, "max": 0.14887, "counts": 679}, "59400": {"idx": 33, "max": 0.16451, "counts": 691}, "61200": {"idx": 34, "max": 0.15677, "counts": 734}, "63000": {"idx": 35, "max": 0.15803, "counts": 770}, "64800": {"idx": 36, "max": 0.177, "counts": 834}, "66600": {"idx": 37, "max": 0.2188, "counts": 891}, "68400": {"idx": 38, "max": 0.2864, "counts": 996}, "70200": {"idx": 39, "max": 0.31094, "counts": 1091}, "72000": {"idx": 40, "max": 0.39463, "counts": 1169}, "73800": {"idx": 41, "max": 0.38736, "counts": 1326}, "75600": {"idx": 42, "max": 0.40126, "counts": 1401}, "77400": {"idx": 43, "max": 0.46841, "counts": 1559}, "79200": {"idx": 44, "max": 0.61894, "counts": 1661}, "81000": {"idx": 45, "max": 0.64103, "counts": 1840}, "82800": {"idx": 46, "max": 0.66205, "counts": 1907}, "84600": {"idx": 47, "max": 0.62722, "counts": 1982}, "86400": {"idx": 48, "max": 0.56593, "counts": 2138}, "88200": {"idx": 49, "max": 0.63581, "counts": 2147}, "90000": {"idx": 50, "max": 0.59071, "counts": 2255}, "91800": {"idx": 51, "max": 0.69277, "counts": 2406}, "93600": {"idx": 52, "max": 0.69277, "counts": 2359}, "95400": {"idx": 53, "max": 0.64514, "counts": 2544}, "97200": {"idx": 54, "max": 0.45722, "counts": 2633}, "99000": {"idx": 55, "max": 0.68698, "counts": 2705}, "100800": {"idx": 56, "max": 0.70241, "counts": 2637}, "102600": {"idx": 57, "max": 1.08251, "counts": 4240}, "104400": {"idx": 58, "max": 1.09883, "counts": 4692}, "106200": {"idx": 59, "max": 1.04056, "counts": 4845}, "108000": {"idx": 60, "max": 0.96253, "counts": 4875}, "109800": {"idx": 61, "max": 1.18558, "counts": 4959}, "111600": {"idx": 62, "max": 1.03298, "counts": 4759}, "113400": {"idx": 63, "max": 0.94566, "counts": 4796}, "115200": {"idx": 64, "max": 0.93534, "counts": 4637}, "117000": {"idx": 65, "max": 0.99063, "counts": 4468}, "118800": {"idx": 66, "max": 1.21281, "counts": 4377}, "120600": {"idx": 67, "max": 0.86947, "counts": 4217}, "122400": {"idx": 68, "max": 1.1218, "counts": 4194}, "124200": {"idx": 69, "max": 1.58508, "counts": 4070}, "126000": {"idx": 70, "max": 1.18379, "counts": 4125}, "127800": {"idx": 71, "max": 1.31689, "counts": 3934}, "129600": {"idx": 72, "max": 0.95883, "counts": 3573}, "131400": {"idx": 73, "max": 0.93606, "counts": 3305}, "133200": {"idx": 74, "max": 0.82485, "counts": 3030}, "135000": {"idx": 75, "max": 0.81094, "counts": 2723}, "136800": {"idx": 76, "max": 0.5564, "counts": 2412}, "138600": {"idx": 77, "max": 0.56219, "counts": 2421}, "140400": {"idx": 78, "max": 0.50355, "counts": 2328}, "142200": {"idx": 79, "max": 0.30163, "counts": 2158}, "144000": {"idx": 80, "max": 0.21114, "counts": 1911}, "145800": {"idx": 81, "max": 0.34104, "counts": 1834}, "147600": {"idx": 82, "max": 0.24555, "counts": 1890}, "149400": {"idx": 83, "max": 0.3013, "counts": 1821}, "151200": {"idx": 84, "max": 0.47477, "counts": 1958}, "153000": {"idx": 85, "max": 0.38552, "counts": 2104}, "154800": {"idx": 86, "max": 0.30131, "counts": 2256}, "156600": {"idx": 87, "max": 0.479, "counts": 2437}, "158400": {"idx": 88, "max": 0.58306, "counts": 2634}, "160200": {"idx": 89, "max": 0.4624, "counts": 2778}, "162000": {"idx": 90, "max": 0.52025, "counts": 3058}, "163800": {"idx": 91, "max": 0.56504, "counts": 3445}, "165600": {"idx": 92, "max": 0.4771, "counts": 3596}, "167400": {"idx": 93, "max": 0.969, "counts": 3900}, "169200": {"idx": 94, "max": 1.44356, "counts": 4121}, "171000": {"idx": 95, "max": 0.85648, "counts": 4159}, "172800": {"idx": 96, "max": 2.00101, "counts": 4464}, "174600": {"idx": 97, "max": 1.38013, "counts": 4606}, "176400": {"idx": 98, "max": 1.1474, "counts": 4799}, "178200": {"idx": 99, "max": 1.33296, "counts": 4954}, "180000": {"idx": 100, "max": 1.50274, "counts": 5281}, "181800": {"idx": 101, "max": 0.87255, "counts": 5122}, "183600": {"idx": 102, "max": 0.95123, "counts": 5106}, "185400": {"idx": 103, "max": 1.34979, "counts": 5036}, "187200": {"idx": 104, "max": 0.94169, "counts": 4812}, "189000": {"idx": 105, "max": 1.02327, "counts": 5175}, "190800": {"idx": 106, "max": 0.73179, "counts": 5062}, "192600": {"idx": 107, "max": 2.54621, "counts": 5580}, "194400": {"idx": 108, "max": 1.90907, "counts": 5563}, "196200": {"idx": 109, "max": 2.52483, "counts": 5414}, "198000": {"idx": 110, "max": 3.86074, "counts": 5940}, "199800": {"idx": 111, "max": 4.71202, "counts": 6130}, "201600": {"idx": 112, "max": 4.56605, "counts": 6238}, "203400": {"idx": 113, "max": 3.28274, "counts": 6147}, "205200": {"idx": 114, "max": 2.19591, "counts": 5771}, "207000": {"idx": 115, "max": 2.14564, "counts": 5402}, "208800": {"idx": 116, "max": 2.5728, "counts": 5063}, "210600": {"idx": 117, "max": 2.61231, "counts": 4865}, "212400": {"idx": 118, "max": 2.199, "counts": 4510}, "214200": {"idx": 119, "max": 1.46697, "counts": 4042}, "216000": {"idx": 120, "max": 1.26242, "counts": 3784}, "217800": {"idx": 121, "max": 1.5798, "counts": 3547}, "219600": {"idx": 122, "max": 1.61432, "counts": 3330}, "221400": {"idx": 123, "max": 1.1727, "counts": 3111}, "223200": {"idx": 124, "max": 0.92441, "counts": 2796}, "225000": {"idx": 125, "max": 0.78612, "counts": 2506}, "226800": {"idx": 126, "max": 0.64587, "counts": 2381}, "228600": {"idx": 127, "max": 0.57549, "counts": 2175}, "230400": {"idx": 128, "max": 0.42988, "counts": 2124}, "232200": {"idx": 129, "max": 0.5147, "counts": 2149}, "234000": {"idx": 130, "max": 0.72637, "counts": 2211}, "235800": {"idx": 131, "max": 0.81393, "counts": 2326}, "237600": {"idx": 132, "max": 1.00186, "counts": 2387}, "239400": {"idx": 133, "max": 1.15127, "counts": 2427}, "241200": {"idx": 134, "max": 1.22473, "counts": 2606}, "243000": {"idx": 135, "max": 1.16018, "counts": 2709}, "244800": {"idx": 136, "max": 1.34968, "counts": 2749}, "246600": {"idx": 137, "max": 1.29268, "counts": 2912}, "248400": {"idx": 138, "max": 1.12989, "counts": 3151}, "250200": {"idx": 139, "max": 1.19186, "counts": 2984}, "252000": {"idx": 140, "max": 0.68367, "counts": 2986}, "253800": {"idx": 141, "max": 0.73858, "counts": 2937}, "255600": {"idx": 142, "max": 0.64283, "counts": 2746}, "257400": {"idx": 143, "max": 0.55467, "counts": 2596}, "259200": {"idx": 144, "max": 0.0, "counts": 0}}}