{"0": {"idx": 0, "max": 7, "counts": 766}, "1800": {"idx": 1, "max": 5, "counts": 1473}, "3600": {"idx": 2, "max": 9, "counts": 2282}, "5400": {"idx": 3, "max": 15, "counts": 3359}, "7200": {"idx": 4, "max": 18, "counts": 4356}, "9000": {"idx": 5, "max": 25, "counts": 5224}, "10800": {"idx": 6, "max": 34, "counts": 5983}, "12600": {"idx": 7, "max": 31, "counts": 6495}, "14400": {"idx": 8, "max": 24, "counts": 5065}, "16200": {"idx": 9, "max": 40, "counts": 4099}, "18000": {"idx": 10, "max": 32, "counts": 3960}, "19800": {"idx": 11, "max": 30, "counts": 4883}, "21600": {"idx": 12, "max": 44, "counts": 6617}, "23400": {"idx": 13, "max": 46, "counts": 6916}, "25200": {"idx": 14, "max": 23, "counts": 5113}, "27000": {"idx": 15, "max": 20, "counts": 4292}, "28800": {"idx": 16, "max": 19, "counts": 4289}, "30600": {"idx": 17, "max": 19, "counts": 4352}, "32400": {"idx": 18, "max": 29, "counts": 4481}, "34200": {"idx": 19, "max": 15, "counts": 4460}, "36000": {"idx": 20, "max": 12, "counts": 2735}, "37800": {"idx": 21, "max": 13, "counts": 2556}, "39600": {"idx": 22, "max": 15, "counts": 2713}, "41400": {"idx": 23, "max": 13, "counts": 2653}, "43200": {"idx": 24, "max": 15, "counts": 2858}, "45000": {"idx": 25, "max": 8, "counts": 3597}, "46800": {"idx": 26, "max": 13, "counts": 3581}, "48600": {"idx": 27, "max": 13, "counts": 3474}, "50400": {"idx": 28, "max": 10, "counts": 3328}, "52200": {"idx": 29, "max": 11, "counts": 3250}, "54000": {"idx": 30, "max": 10, "counts": 3177}, "55800": {"idx": 31, "max": 8, "counts": 3072}, "57600": {"idx": 32, "max": 36, "counts": 2952}, "59400": {"idx": 33, "max": 31, "counts": 3004}, "61200": {"idx": 34, "max": 29, "counts": 2954}, "63000": {"idx": 35, "max": 23, "counts": 3044}, "64800": {"idx": 36, "max": 29, "counts": 3131}, "66600": {"idx": 37, "max": 21, "counts": 3443}, "68400": {"idx": 38, "max": 26, "counts": 3684}, "70200": {"idx": 39, "max": 27, "counts": 3888}, "72000": {"idx": 40, "max": 21, "counts": 4149}, "73800": {"idx": 41, "max": 24, "counts": 4281}, "75600": {"idx": 42, "max": 20, "counts": 4502}, "77400": {"idx": 43, "max": 17, "counts": 4883}, "79200": {"idx": 44, "max": 20, "counts": 5160}, "81000": {"idx": 45, "max": 21, "counts": 5550}, "82800": {"idx": 46, "max": 25, "counts": 6027}, "84600": {"idx": 47, "max": 22, "counts": 6321}, "86400": {"idx": 48, "max": 32, "counts": 6699}, "88200": {"idx": 49, "max": 21, "counts": 6818}, "90000": {"idx": 50, "max": 15, "counts": 7242}, "91800": {"idx": 51, "max": 17, "counts": 7596}, "93600": {"idx": 52, "max": 19, "counts": 7821}, "95400": {"idx": 53, "max": 14, "counts": 7883}, "97200": {"idx": 54, "max": 21, "counts": 8348}, "99000": {"idx": 55, "max": 23, "counts": 8874}, "100800": {"idx": 56, "max": 22, "counts": 9179}, "102600": {"idx": 57, "max": 25, "counts": 13893}, "104400": {"idx": 58, "max": 38, "counts": 15956}, "106200": {"idx": 59, "max": 47, "counts": 16138}, "108000": {"idx": 60, "max": 31, "counts": 15806}, "109800": {"idx": 61, "max": 15, "counts": 15752}, "111600": {"idx": 62, "max": 25, "counts": 15622}, "113400": {"idx": 63, "max": 18, "counts": 15767}, "115200": {"idx": 64, "max": 29, "counts": 15953}, "117000": {"idx": 65, "max": 19, "counts": 15626}, "118800": {"idx": 66, "max": 23, "counts": 15935}, "120600": {"idx": 67, "max": 42, "counts": 15929}, "122400": {"idx": 68, "max": 36, "counts": 15606}, "124200": {"idx": 69, "max": 215, "counts": 18723}, "126000": {"idx": 70, "max": 59, "counts": 24557}, "127800": {"idx": 71, "max": 38, "counts": 23189}, "129600": {"idx": 72, "max": 24, "counts": 19968}, "131400": {"idx": 73, "max": 21, "counts": 16547}, "133200": {"idx": 74, "max": 17, "counts": 14403}, "135000": {"idx": 75, "max": 17, "counts": 13127}, "136800": {"idx": 76, "max": 18, "counts": 11926}, "138600": {"idx": 77, "max": 47, "counts": 11188}, "140400": {"idx": 78, "max": 30, "counts": 10597}, "142200": {"idx": 79, "max": 15, "counts": 10119}, "144000": {"idx": 80, "max": 10, "counts": 9820}, "145800": {"idx": 81, "max": 9, "counts": 9937}, "147600": {"idx": 82, "max": 26, "counts": 10350}, "149400": {"idx": 83, "max": 22, "counts": 10205}, "151200": {"idx": 84, "max": 35, "counts": 10656}, "153000": {"idx": 85, "max": 22, "counts": 10682}, "154800": {"idx": 86, "max": 23, "counts": 10856}, "156600": {"idx": 87, "max": 24, "counts": 11120}, "158400": {"idx": 88, "max": 28, "counts": 11624}, "160200": {"idx": 89, "max": 31, "counts": 11922}, "162000": {"idx": 90, "max": 25, "counts": 12458}, "163800": {"idx": 91, "max": 36, "counts": 13147}, "165600": {"idx": 92, "max": 22, "counts": 13595}, "167400": {"idx": 93, "max": 30, "counts": 14160}, "169200": {"idx": 94, "max": 26, "counts": 14804}, "171000": {"idx": 95, "max": 27, "counts": 15389}, "172800": {"idx": 96, "max": 25, "counts": 15756}, "174600": {"idx": 97, "max": 40, "counts": 16759}, "176400": {"idx": 98, "max": 52, "counts": 18233}, "178200": {"idx": 99, "max": 55, "counts": 19408}, "180000": {"idx": 100, "max": 47, "counts": 20308}, "181800": {"idx": 101, "max": 43, "counts": 20318}, "183600": {"idx": 102, "max": 57, "counts": 20187}, "185400": {"idx": 103, "max": 47, "counts": 18632}, "187200": {"idx": 104, "max": 44, "counts": 19348}, "189000": {"idx": 105, "max": 50, "counts": 20370}, "190800": {"idx": 106, "max": 51, "counts": 20730}, "192600": {"idx": 107, "max": 51, "counts": 20645}, "194400": {"idx": 108, "max": 46, "counts": 20259}, "196200": {"idx": 109, "max": 52, "counts": 19881}, "198000": {"idx": 110, "max": 49, "counts": 20100}, "199800": {"idx": 111, "max": 39, "counts": 20093}, "201600": {"idx": 112, "max": 52, "counts": 20094}, "203400": {"idx": 113, "max": 49, "counts": 20112}, "205200": {"idx": 114, "max": 55, "counts": 19631}, "207000": {"idx": 115, "max": 57, "counts": 19797}, "208800": {"idx": 116, "max": 52, "counts": 19475}, "210600": {"idx": 117, "max": 44, "counts": 19022}, "212400": {"idx": 118, "max": 32, "counts": 18924}, "214200": {"idx": 119, "max": 57, "counts": 18352}, "216000": {"idx": 120, "max": 45, "counts": 18510}, "217800": {"idx": 121, "max": 44, "counts": 17499}, "219600": {"idx": 122, "max": 53, "counts": 16257}, "221400": {"idx": 123, "max": 69, "counts": 16928}, "223200": {"idx": 124, "max": 52, "counts": 16286}, "225000": {"idx": 125, "max": 44, "counts": 14650}, "226800": {"idx": 126, "max": 49, "counts": 12621}, "228600": {"idx": 127, "max": 53, "counts": 11364}, "230400": {"idx": 128, "max": 36, "counts": 10771}, "232200": {"idx": 129, "max": 33, "counts": 10894}, "234000": {"idx": 130, "max": 31, "counts": 11197}, "235800": {"idx": 131, "max": 21, "counts": 11868}, "237600": {"idx": 132, "max": 30, "counts": 12831}, "239400": {"idx": 133, "max": 27, "counts": 13837}, "241200": {"idx": 134, "max": 27, "counts": 14255}, "243000": {"idx": 135, "max": 24, "counts": 14539}, "244800": {"idx": 136, "max": 21, "counts": 14703}, "246600": {"idx": 137, "max": 25, "counts": 15477}, "248400": {"idx": 138, "max": 26, "counts": 15867}, "250200": {"idx": 139, "max": 32, "counts": 16344}, "252000": {"idx": 140, "max": 28, "counts": 16224}, "253800": {"idx": 141, "max": 41, "counts": 16684}, "255600": {"idx": 142, "max": 33, "counts": 15695}, "257400": {"idx": 143, "max": 25, "counts": 14915}, "259200": {"idx": 144, "max": 0, "counts": 0}}