{"0": {"idx": 0, "max": 1, "counts": 112}, "1800": {"idx": 1, "max": 2, "counts": 258}, "3600": {"idx": 2, "max": 3, "counts": 419}, "5400": {"idx": 3, "max": 3, "counts": 641}, "7200": {"idx": 4, "max": 3, "counts": 833}, "9000": {"idx": 5, "max": 4, "counts": 1068}, "10800": {"idx": 6, "max": 3, "counts": 1152}, "12600": {"idx": 7, "max": 4, "counts": 1216}, "14400": {"idx": 8, "max": 3, "counts": 964}, "16200": {"idx": 9, "max": 5, "counts": 795}, "18000": {"idx": 10, "max": 6, "counts": 753}, "19800": {"idx": 11, "max": 6, "counts": 930}, "21600": {"idx": 12, "max": 8, "counts": 1226}, "23400": {"idx": 13, "max": 5, "counts": 1197}, "25200": {"idx": 14, "max": 4, "counts": 853}, "27000": {"idx": 15, "max": 4, "counts": 716}, "28800": {"idx": 16, "max": 3, "counts": 631}, "30600": {"idx": 17, "max": 3, "counts": 703}, "32400": {"idx": 18, "max": 3, "counts": 692}, "34200": {"idx": 19, "max": 3, "counts": 708}, "36000": {"idx": 20, "max": 3, "counts": 415}, "37800": {"idx": 21, "max": 3, "counts": 423}, "39600": {"idx": 22, "max": 2, "counts": 412}, "41400": {"idx": 23, "max": 2, "counts": 445}, "43200": {"idx": 24, "max": 2, "counts": 458}, "45000": {"idx": 25, "max": 4, "counts": 605}, "46800": {"idx": 26, "max": 3, "counts": 677}, "48600": {"idx": 27, "max": 3, "counts": 684}, "50400": {"idx": 28, "max": 4, "counts": 769}, "52200": {"idx": 29, "max": 4, "counts": 756}, "54000": {"idx": 30, "max": 3, "counts": 838}, "55800": {"idx": 31, "max": 6, "counts": 928}, "57600": {"idx": 32, "max": 7, "counts": 1006}, "59400": {"idx": 33, "max": 7, "counts": 1068}, "61200": {"idx": 34, "max": 11, "counts": 1088}, "63000": {"idx": 35, "max": 10, "counts": 1206}, "64800": {"idx": 36, "max": 11, "counts": 1335}, "66600": {"idx": 37, "max": 14, "counts": 1401}, "68400": {"idx": 38, "max": 13, "counts": 1465}, "70200": {"idx": 39, "max": 9, "counts": 1549}, "72000": {"idx": 40, "max": 8, "counts": 1595}, "73800": {"idx": 41, "max": 8, "counts": 1606}, "75600": {"idx": 42, "max": 12, "counts": 1687}, "77400": {"idx": 43, "max": 14, "counts": 1769}, "79200": {"idx": 44, "max": 9, "counts": 1929}, "81000": {"idx": 45, "max": 9, "counts": 2096}, "82800": {"idx": 46, "max": 13, "counts": 2186}, "84600": {"idx": 47, "max": 10, "counts": 2248}, "86400": {"idx": 48, "max": 10, "counts": 2301}, "88200": {"idx": 49, "max": 12, "counts": 2334}, "90000": {"idx": 50, "max": 18, "counts": 2442}, "91800": {"idx": 51, "max": 7, "counts": 2448}, "93600": {"idx": 52, "max": 10, "counts": 2483}, "95400": {"idx": 53, "max": 10, "counts": 2577}, "97200": {"idx": 54, "max": 12, "counts": 2625}, "99000": {"idx": 55, "max": 8, "counts": 2827}, "100800": {"idx": 56, "max": 20, "counts": 2923}, "102600": {"idx": 57, "max": 21, "counts": 4690}, "104400": {"idx": 58, "max": 24, "counts": 5215}, "106200": {"idx": 59, "max": 23, "counts": 5154}, "108000": {"idx": 60, "max": 20, "counts": 4897}, "109800": {"idx": 61, "max": 18, "counts": 4579}, "111600": {"idx": 62, "max": 22, "counts": 4456}, "113400": {"idx": 63, "max": 18, "counts": 4295}, "115200": {"idx": 64, "max": 14, "counts": 3845}, "117000": {"idx": 65, "max": 7, "counts": 3468}, "118800": {"idx": 66, "max": 10, "counts": 3145}, "120600": {"idx": 67, "max": 13, "counts": 3095}, "122400": {"idx": 68, "max": 11, "counts": 2726}, "124200": {"idx": 69, "max": 82, "counts": 3955}, "126000": {"idx": 70, "max": 16, "counts": 5293}, "127800": {"idx": 71, "max": 12, "counts": 4976}, "129600": {"idx": 72, "max": 13, "counts": 4212}, "131400": {"idx": 73, "max": 8, "counts": 3707}, "133200": {"idx": 74, "max": 16, "counts": 3265}, "135000": {"idx": 75, "max": 9, "counts": 3085}, "136800": {"idx": 76, "max": 6, "counts": 3042}, "138600": {"idx": 77, "max": 11, "counts": 2947}, "140400": {"idx": 78, "max": 7, "counts": 3049}, "142200": {"idx": 79, "max": 8, "counts": 2855}, "144000": {"idx": 80, "max": 8, "counts": 2918}, "145800": {"idx": 81, "max": 6, "counts": 3141}, "147600": {"idx": 82, "max": 7, "counts": 3280}, "149400": {"idx": 83, "max": 8, "counts": 3313}, "151200": {"idx": 84, "max": 10, "counts": 3329}, "153000": {"idx": 85, "max": 10, "counts": 3534}, "154800": {"idx": 86, "max": 10, "counts": 3524}, "156600": {"idx": 87, "max": 9, "counts": 3520}, "158400": {"idx": 88, "max": 14, "counts": 3775}, "160200": {"idx": 89, "max": 21, "counts": 3840}, "162000": {"idx": 90, "max": 21, "counts": 3909}, "163800": {"idx": 91, "max": 15, "counts": 3971}, "165600": {"idx": 92, "max": 15, "counts": 4031}, "167400": {"idx": 93, "max": 14, "counts": 4157}, "169200": {"idx": 94, "max": 14, "counts": 4095}, "171000": {"idx": 95, "max": 16, "counts": 4280}, "172800": {"idx": 96, "max": 15, "counts": 4062}, "174600": {"idx": 97, "max": 17, "counts": 4036}, "176400": {"idx": 98, "max": 14, "counts": 4158}, "178200": {"idx": 99, "max": 18, "counts": 4348}, "180000": {"idx": 100, "max": 25, "counts": 4538}, "181800": {"idx": 101, "max": 28, "counts": 4230}, "183600": {"idx": 102, "max": 25, "counts": 4200}, "185400": {"idx": 103, "max": 22, "counts": 3720}, "187200": {"idx": 104, "max": 16, "counts": 3993}, "189000": {"idx": 105, "max": 8, "counts": 4036}, "190800": {"idx": 106, "max": 17, "counts": 3838}, "192600": {"idx": 107, "max": 7, "counts": 3800}, "194400": {"idx": 108, "max": 12, "counts": 3567}, "196200": {"idx": 109, "max": 16, "counts": 3419}, "198000": {"idx": 110, "max": 20, "counts": 3155}, "199800": {"idx": 111, "max": 19, "counts": 3098}, "201600": {"idx": 112, "max": 17, "counts": 2944}, "203400": {"idx": 113, "max": 15, "counts": 2891}, "205200": {"idx": 114, "max": 19, "counts": 2768}, "207000": {"idx": 115, "max": 30, "counts": 2741}, "208800": {"idx": 116, "max": 19, "counts": 2575}, "210600": {"idx": 117, "max": 24, "counts": 2802}, "212400": {"idx": 118, "max": 42, "counts": 3851}, "214200": {"idx": 119, "max": 93, "counts": 4875}, "216000": {"idx": 120, "max": 87, "counts": 5096}, "217800": {"idx": 121, "max": 99, "counts": 4343}, "219600": {"idx": 122, "max": 69, "counts": 3878}, "221400": {"idx": 123, "max": 41, "counts": 3689}, "223200": {"idx": 124, "max": 58, "counts": 3438}, "225000": {"idx": 125, "max": 55, "counts": 3428}, "226800": {"idx": 126, "max": 40, "counts": 3379}, "228600": {"idx": 127, "max": 42, "counts": 3526}, "230400": {"idx": 128, "max": 35, "counts": 3792}, "232200": {"idx": 129, "max": 41, "counts": 3962}, "234000": {"idx": 130, "max": 29, "counts": 3903}, "235800": {"idx": 131, "max": 24, "counts": 3683}, "237600": {"idx": 132, "max": 18, "counts": 3856}, "239400": {"idx": 133, "max": 37, "counts": 4008}, "241200": {"idx": 134, "max": 35, "counts": 4214}, "243000": {"idx": 135, "max": 31, "counts": 4395}, "244800": {"idx": 136, "max": 44, "counts": 4461}, "246600": {"idx": 137, "max": 68, "counts": 4461}, "248400": {"idx": 138, "max": 65, "counts": 4564}, "250200": {"idx": 139, "max": 52, "counts": 4649}, "252000": {"idx": 140, "max": 56, "counts": 4574}, "253800": {"idx": 141, "max": 40, "counts": 4286}, "255600": {"idx": 142, "max": 37, "counts": 4059}, "257400": {"idx": 143, "max": 29, "counts": 3704}, "259200": {"idx": 144, "max": 0, "counts": 0}}